dksinha/__init__.py
dksinha/dksinha.py
dksinha-0.1.dist-info/METADATA
dksinha-0.1.dist-info/WHEEL
dksinha-0.1.dist-info/top_level.txt
dksinha-0.1.dist-info/RECORD
